Metadata-Version: 1.0
Name: tictacJiya
Version: 0.1
Summary: TicTac Jiya game, tictactoe game created by Jiya with a little twist
Home-page: UNKNOWN
Author: Jiya
Author-email: UNKNOWN
License: UNKNOWN
Platform: UNKNOWN
